[
  {
    "title": "취속복원(1)",
    "category": "항공&여행",
    "datetime": "07-03",
    "company": "아고다"
  },
  {
    "title": "좀전에 문의한 내용에 덧붙일 내용이 있어서 …(1)",
    "category": "항공&여행",
    "datetime": "07-03",
    "company": "여기어때"
  },
  {
    "title": "단기렌트 취소 환불 불가(1)",
    "category": "항공&여행",
    "datetime": "07-03",
    "company": "33m2"
  },
  {
    "title": "숙박업 (1)",
    "category": "항공&여행",
    "datetime": "07-03",
    "company": "http://sanj.co.kr/"
  },
  {
    "title": "취소와 환불 둘 다 불가하다네요.(1)",
    "category": "항공&여행",
    "datetime": "07-03",
    "company": "여기어때"
  },
  {
    "title": "불충분한 안내로 인한 세금 발생(1)",
    "category": "항공&여행",
    "datetime": "07-03",
    "company": "에어텔 닷컴"
  },
  {
    "title": "취소수수료가 너무 많이 나옴(1)",
    "category": "항공&여행",
    "datetime": "07-03",
    "company": "마이트랩"
  },
  {
    "title": "예약취소후 환불없음(1)",
    "category": "항공&여행",
    "datetime": "07-03",
    "company": "익스피디아"
  },
  {
    "title": "돈을 돌려받지 못하고있습니다 .(1)",
    "category": "항공&여행",
    "datetime": "07-02",
    "company": "아고다"
  },
  {
    "title": "항공권 결제 후 3분이내 결제 취소 요청했는…(1)",
    "category": "항공&여행",
    "datetime": "07-02",
    "company": "고투게이트코리아 유한책임회사 가맹점"
  },
  {
    "title": "호텔 온라인 이중계약 환불불가(1)",
    "category": "항공&여행",
    "datetime": "07-02",
    "company": "아고다"
  },
  {
    "title": "수화물 파손으로 인한 제주항공 고발합니다.(1)",
    "category": "항공&여행",
    "datetime": "07-02",
    "company": "제주항공"
  },
  {
    "title": "여기 어때 환불에 관해(1)",
    "category": "항공&여행",
    "datetime": "07-02",
    "company": "여기어때"
  }
]
